{"PAGE_NUMBER":0,"FileName_Large":"mr0008.jpg","FileName_Thumb":"","PageWidth":1700,"PageHeight":2200,"Document_Text":"U.S. Department of Justice\nAttorney Work Produet // May Contain Material Proteeted Under Fed. R. Crim. P. 610)\n","Document_Text_Fixed":"","PARAGRAPHS":[{"TEXT":"U.S.DepartmentofJusticeAttorneyWorkProduet//MayContainMaterialProteetedUnderFed.R.Crim.P.610)","TEXT_fixed":"","WORDS":[{"TEXT":"U","BB":{"AAX":683,"AAY":67,"BBX":691,"BBY":67,"CCX":691,"CCY":98,"DDX":683,"DDY":98}},{"TEXT":".","BB":{"AAX":702,"AAY":67,"BBX":710,"BBY":67,"CCX":710,"CCY":98,"DDX":702,"DDY":98}},{"TEXT":"S","BB":{"AAX":715,"AAY":67,"BBX":723,"BBY":67,"CCX":723,"CCY":98,"DDX":715,"DDY":98}},{"TEXT":".","BB":{"AAX":727,"AAY":66,"BBX":735,"BBY":66,"CCX":735,"CCY":97,"DDX":727,"DDY":97}},{"TEXT":"Department","BB":{"AAX":742,"AAY":66,"BBX":759,"BBY":66,"CCX":759,"CCY":97,"DDX":742,"DDY":97}},{"TEXT":"of","BB":{"AAX":901,"AAY":66,"BBX":914,"BBY":66,"CCX":914,"CCY":97,"DDX":901,"DDY":97}},{"TEXT":"Justice","BB":{"AAX":939,"AAY":66,"BBX":946,"BBY":66,"CCX":946,"CCY":97,"DDX":939,"DDY":97}},{"TEXT":"Attorney","BB":{"AAX":300,"AAY":108,"BBX":312,"BBY":108,"CCX":312,"CCY":140,"DDX":300,"DDY":140}},{"TEXT":"Work","BB":{"AAX":413,"AAY":108,"BBX":436,"BBY":108,"CCX":436,"CCY":140,"DDX":413,"DDY":140}},{"TEXT":"Produet","BB":{"AAX":498,"AAY":107,"BBX":510,"BBY":107,"CCX":510,"CCY":139,"DDX":498,"DDY":139}},{"TEXT":"/","BB":{"AAX":605,"AAY":107,"BBX":613,"BBY":107,"CCX":613,"CCY":139,"DDX":605,"DDY":139}},{"TEXT":"/","BB":{"AAX":615,"AAY":107,"BBX":623,"BBY":107,"CCX":623,"CCY":139,"DDX":615,"DDY":139}},{"TEXT":"May","BB":{"AAX":624,"AAY":107,"BBX":647,"BBY":107,"CCX":647,"CCY":139,"DDX":624,"DDY":139}},{"TEXT":"Contain","BB":{"AAX":697,"AAY":107,"BBX":713,"BBY":107,"CCX":713,"CCY":139,"DDX":697,"DDY":139}},{"TEXT":"Material","BB":{"AAX":799,"AAY":106,"BBX":822,"BBY":106,"CCX":822,"CCY":138,"DDX":799,"DDY":138}},{"TEXT":"Proteeted","BB":{"AAX":920,"AAY":106,"BBX":933,"BBY":106,"CCX":933,"CCY":138,"DDX":920,"DDY":138}},{"TEXT":"Under","BB":{"AAX":1050,"AAY":105,"BBX":1066,"BBY":105,"CCX":1066,"CCY":137,"DDX":1050,"DDY":137}},{"TEXT":"Fed","BB":{"AAX":1137,"AAY":105,"BBX":1150,"BBY":105,"CCX":1150,"CCY":137,"DDX":1137,"DDY":137}},{"TEXT":".","BB":{"AAX":1186,"AAY":105,"BBX":1194,"BBY":105,"CCX":1194,"CCY":137,"DDX":1186,"DDY":137}},{"TEXT":"R","BB":{"AAX":1203,"AAY":105,"BBX":1211,"BBY":105,"CCX":1211,"CCY":137,"DDX":1203,"DDY":137}},{"TEXT":".","BB":{"AAX":1223,"AAY":105,"BBX":1231,"BBY":105,"CCX":1231,"CCY":137,"DDX":1223,"DDY":137}},{"TEXT":"Crim","BB":{"AAX":1240,"AAY":105,"BBX":1253,"BBY":105,"CCX":1253,"CCY":137,"DDX":1240,"DDY":137}},{"TEXT":".","BB":{"AAX":1305,"AAY":104,"BBX":1313,"BBY":104,"CCX":1313,"CCY":136,"DDX":1305,"DDY":136}},{"TEXT":"P","BB":{"AAX":1322,"AAY":104,"BBX":1330,"BBY":104,"CCX":1330,"CCY":136,"DDX":1322,"DDY":136}},{"TEXT":".","BB":{"AAX":1338,"AAY":104,"BBX":1346,"BBY":104,"CCX":1346,"CCY":136,"DDX":1338,"DDY":136}},{"TEXT":"610","BB":{"AAX":1353,"AAY":104,"BBX":1365,"BBY":104,"CCX":1365,"CCY":136,"DDX":1353,"DDY":136}},{"TEXT":")","BB":{"AAX":1394,"AAY":104,"BBX":1402,"BBY":104,"CCX":1402,"CCY":136,"DDX":1394,"DDY":136}}],"BB":{"AAX":300,"AAY":68,"BBX":1402,"BBY":64,"CCX":1402,"CCY":136,"DDX":300,"DDY":140}}],"WC":null}